[
  [
    {
      "березеньчик": {
        "OpencorporaTag": [
          "NOUN",
          "inan",
          "masc sing",
          "nomn"
        ],
        "normal_form": "березеньчик"
      }
    },
    {
      "свилеват": {
        "OpencorporaTag": [
          "ADJS",
          "Qual masc",
          "sing"
        ],
        "normal_form": "свилеватый"
      }
    }
  ],
  [
    {
      "свилеватый": {
        "OpencorporaTag": [
          "ADJF",
          "Qual masc",
          "sing",
          "nomn"
        ],
        "normal_form": "свилеватый"
      }
    },
    {
      "кудреват": {
        "OpencorporaTag": [
          "ADJS",
          "Qual masc",
          "sing"
        ],
        "normal_form": "кудреватый"
      }
    }
  ],
  [
    {
      "а": {
        "OpencorporaTag": [
          "CONJ"
        ],
        "normal_form": "а"
      }
    },
    {
      "кто": {
        "OpencorporaTag": [
          "NPRO",
          "masc sing",
          "nomn"
        ],
        "normal_form": "кто"
      }
    },
    {
      "у": {
        "OpencorporaTag": [
          "PREP"
        ],
        "normal_form": "у"
      }
    },
    {
      "нас": {
        "OpencorporaTag": [
          "NPRO",
          "1per plur",
          "gent"
        ],
        "normal_form": "мы"
      }
    },
    {
      "ходит": {
        "OpencorporaTag": [
          "VERB",
          "impf",
          "intr sing",
          "3per",
          "pres",
          "indc"
        ],
        "normal_form": "ходить"
      }
    },
    {
      "холост": {
        "OpencorporaTag": [
          "ADJS masc",
          "sing"
        ],
        "normal_form": "холостой"
      }
    }
  ],
  [
    {
      "а": {
        "OpencorporaTag": [
          "CONJ"
        ],
        "normal_form": "а"
      }
    },
    {
      "кто": {
        "OpencorporaTag": [
          "NPRO",
          "masc sing",
          "nomn"
        ],
        "normal_form": "кто"
      }
    },
    {
      "у": {
        "OpencorporaTag": [
          "PREP"
        ],
        "normal_form": "у"
      }
    },
    {
      "нас": {
        "OpencorporaTag": [
          "NPRO",
          "1per plur",
          "gent"
        ],
        "normal_form": "мы"
      }
    },
    {
      "неженат": {
        "OpencorporaTag": [
          "ADJS",
          "Qual masc",
          "sing"
        ],
        "normal_form": "неженатый"
      }
    }
  ],
  [
    {
      "имя": {
        "OpencorporaTag": [
          "NOUN",
          "inan",
          "neut sing",
          "accs"
        ],
        "normal_form": "имя"
      }
    },
    {
      "ходит": {
        "OpencorporaTag": [
          "VERB",
          "impf",
          "intr sing",
          "3per",
          "pres",
          "indc"
        ],
        "normal_form": "ходить"
      }
    },
    {
      "холост": {
        "OpencorporaTag": [
          "ADJS masc",
          "sing"
        ],
        "normal_form": "холостой"
      }
    }
  ],
  [
    {
      "отчество": {
        "OpencorporaTag": [
          "NOUN",
          "inan",
          "neut sing",
          "nomn"
        ],
        "normal_form": "отчество"
      }
    },
    {
      "неженат": {
        "OpencorporaTag": [
          "ADJS",
          "Qual masc",
          "sing"
        ],
        "normal_form": "неженатый"
      }
    }
  ],
  [
    {
      "ему": {
        "OpencorporaTag": [
          "NPRO",
          "masc",
          "3per",
          "Anph sing",
          "datv"
        ],
        "normal_form": "он"
      }
    },
    {
      "маменька": {
        "OpencorporaTag": [
          "NOUN",
          "anim",
          "femn sing",
          "nomn"
        ],
        "normal_form": "маменька"
      }
    },
    {
      "сказала": {
        "OpencorporaTag": [
          "VERB",
          "perf",
          "tran femn",
          "sing",
          "past",
          "indc"
        ],
        "normal_form": "сказать"
      }
    }
  ],
  [
    {
      "сударыня": {
        "OpencorporaTag": [
          "NOUN",
          "anim",
          "femn sing",
          "nomn"
        ],
        "normal_form": "сударыня"
      }
    },
    {
      "говорила": {
        "OpencorporaTag": [
          "VERB",
          "impf",
          "tran femn",
          "sing",
          "past",
          "indc"
        ],
        "normal_form": "говорить"
      }
    }
  ],
  [
    {
      "все": {
        "OpencorporaTag": [
          "ADJF",
          "Apro plur",
          "nomn"
        ],
        "normal_form": "весь"
      }
    },
    {
      "жениться": {
        "OpencorporaTag": [
          "INFN",
          "perf",
          "intr"
        ],
        "normal_form": "жениться"
      }
    },
    {
      "велела": {
        "OpencorporaTag": [
          "VERB",
          "perf",
          "intr femn",
          "sing",
          "past",
          "indc"
        ],
        "normal_form": "велеть"
      }
    }
  ],
  [
    {
      "женись": {
        "OpencorporaTag": [
          "VERB",
          "perf",
          "intr sing",
          "impr",
          "excl"
        ],
        "normal_form": "жениться"
      }
    },
    {
      "женись": {
        "OpencorporaTag": [
          "VERB",
          "perf",
          "intr sing",
          "impr",
          "excl"
        ],
        "normal_form": "жениться"
      }
    },
    {
      "дитятко": {
        "OpencorporaTag": [
          "NOUN",
          "anim",
          "neut sing",
          "nomn"
        ],
        "normal_form": "дитятко"
      }
    }
  ],
  [
    {
      "женись": {
        "OpencorporaTag": [
          "VERB",
          "perf",
          "intr sing",
          "impr",
          "excl"
        ],
        "normal_form": "жениться"
      }
    },
    {
      "сынок": {
        "OpencorporaTag": [
          "NOUN",
          "anim",
          "masc sing",
          "nomn"
        ],
        "normal_form": "сынок"
      }
    },
    {
      "милый": {
        "OpencorporaTag": [
          "ADJF",
          "Subx",
          "Qual masc",
          "sing",
          "nomn"
        ],
        "normal_form": "милый"
      }
    },
    {
      "": {
        "OpencorporaTag": [
          "UNKN"
        ],
        "normal_form": ""
      }
    }
  ],
  [
    {
      "": {
        "OpencorporaTag": [
          "UNKN"
        ],
        "normal_form": ""
      }
    },
    {
      "сударыня": {
        "OpencorporaTag": [
          "NOUN",
          "anim",
          "femn sing",
          "nomn"
        ],
        "normal_form": "сударыня"
      }
    },
    {
      "маменька": {
        "OpencorporaTag": [
          "NOUN",
          "anim",
          "femn sing",
          "nomn"
        ],
        "normal_form": "маменька"
      }
    }
  ],
  [
    {
      "на": {
        "OpencorporaTag": [
          "PREP"
        ],
        "normal_form": "на"
      }
    },
    {
      "что": {
        "OpencorporaTag": [
          "CONJ"
        ],
        "normal_form": "что"
      }
    },
    {
      "мне": {
        "OpencorporaTag": [
          "NPRO",
          "1per sing",
          "datv"
        ],
        "normal_form": "я"
      }
    },
    {
      "женитися": {
        "OpencorporaTag": [
          "NOUN",
          "anim",
          "femn",
          "Name sing",
          "nomn"
        ],
        "normal_form": "женитися"
      }
    }
  ],
  [
    {
      "и": {
        "OpencorporaTag": [
          "CONJ"
        ],
        "normal_form": "и"
      }
    },
    {
      "так": {
        "OpencorporaTag": [
          "CONJ"
        ],
        "normal_form": "так"
      }
    },
    {
      "барышни": {
        "OpencorporaTag": [
          "NOUN",
          "anim",
          "femn plur",
          "nomn"
        ],
        "normal_form": "барышня"
      }
    },
    {
      "меня": {
        "OpencorporaTag": [
          "NPRO",
          "1per sing",
          "accs"
        ],
        "normal_form": "я"
      }
    },
    {
      "любят": {
        "OpencorporaTag": [
          "VERB",
          "impf",
          "tran plur",
          "3per",
          "pres",
          "indc"
        ],
        "normal_form": "любить"
      }
    }
  ],
  [
    {
      "молодушки": {
        "OpencorporaTag": [
          "NOUN",
          "anim",
          "femn sing",
          "gent"
        ],
        "normal_form": "молодушка"
      }
    },
    {
      "всегда": {
        "OpencorporaTag": [
          "ADVB"
        ],
        "normal_form": "всегда"
      }
    },
    {
      "хвалят": {
        "OpencorporaTag": [
          "VERB",
          "impf",
          "tran plur",
          "3per",
          "pres",
          "indc"
        ],
        "normal_form": "хвалить"
      }
    }
  ],
  [
    {
      "за": {
        "OpencorporaTag": [
          "PREP"
        ],
        "normal_form": "за"
      }
    },
    {
      "компанью": {
        "OpencorporaTag": [
          "NOUN",
          "anim",
          "femn",
          "Name sing",
          "accs"
        ],
        "normal_form": "компанья"
      }
    },
    {
      "принимают": {
        "OpencorporaTag": [
          "VERB",
          "impf",
          "tran plur",
          "3per",
          "pres",
          "indc"
        ],
        "normal_form": "принимать"
      }
    }
  ],
  [
    {
      "чаем-кофьем": {
        "OpencorporaTag": [
          "NOUN",
          "inan",
          "masc sing",
          "ablt"
        ],
        "normal_form": "чай-кофие"
      }
    },
    {
      "угощают": {
        "OpencorporaTag": [
          "VERB",
          "impf",
          "tran plur",
          "3per",
          "pres",
          "indc"
        ],
        "normal_form": "угощать"
      }
    }
  ],
  [
    {
      "конфетами": {
        "OpencorporaTag": [
          "NOUN",
          "inan",
          "femn plur",
          "ablt"
        ],
        "normal_form": "конфета"
      }
    },
    {
      "упрошают": {
        "OpencorporaTag": [
          "VERB",
          "impf",
          "tran plur",
          "3per",
          "pres",
          "indc"
        ],
        "normal_form": "упрошать"
      }
    }
  ],
  [
    {
      "что": {
        "OpencorporaTag": [
          "CONJ"
        ],
        "normal_form": "что"
      }
    },
    {
      "имя": {
        "OpencorporaTag": [
          "NOUN",
          "inan",
          "neut sing",
          "accs"
        ],
        "normal_form": "имя"
      }
    },
    {
      "называют": {
        "OpencorporaTag": [
          "VERB",
          "impf",
          "tran plur",
          "3per",
          "pres",
          "indc"
        ],
        "normal_form": "называть"
      }
    }
  ],
  [
    {
      "отчество": {
        "OpencorporaTag": [
          "NOUN",
          "inan",
          "neut sing",
          "nomn"
        ],
        "normal_form": "отчество"
      }
    },
    {
      "величают": {
        "OpencorporaTag": [
          "VERB",
          "impf",
          "tran plur",
          "3per",
          "pres",
          "indc"
        ],
        "normal_form": "величать"
      }
    }
  ]
]