[
  [
    {
      "как": {
        "OpencorporaTag": [
          "CONJ"
        ],
        "normal_form": "как"
      }
    },
    {
      "ты": {
        "OpencorporaTag": [
          "NPRO",
          "2per sing",
          "nomn"
        ],
        "normal_form": "ты"
      }
    },
    {
      "батюшка": {
        "OpencorporaTag": [
          "NOUN",
          "anim",
          "masc sing",
          "nomn"
        ],
        "normal_form": "батюшка"
      }
    },
    {
      "славный": {
        "OpencorporaTag": [
          "ADJF",
          "Qual masc",
          "sing",
          "nomn"
        ],
        "normal_form": "славный"
      }
    },
    {
      "тихій": {
        "OpencorporaTag": [
          "VERB",
          "impf",
          "tran sing",
          "impr",
          "excl"
        ],
        "normal_form": "тихіть"
      }
    },
    {
      "дон": {
        "OpencorporaTag": [
          "NOUN",
          "anim",
          "masc",
          "Name sing",
          "nomn"
        ],
        "normal_form": "дон"
      }
    }
  ],
  [
    {
      "ты": {
        "OpencorporaTag": [
          "NPRO",
          "2per sing",
          "nomn"
        ],
        "normal_form": "ты"
      }
    },
    {
      "кормилец": {
        "OpencorporaTag": [
          "NOUN",
          "anim",
          "masc sing",
          "nomn"
        ],
        "normal_form": "кормилец"
      }
    },
    {
      "наш": {
        "OpencorporaTag": [
          "ADJF",
          "Apro masc",
          "sing",
          "nomn"
        ],
        "normal_form": "наш"
      }
    },
    {
      "дон": {
        "OpencorporaTag": [
          "NOUN",
          "anim",
          "masc",
          "Name sing",
          "nomn"
        ],
        "normal_form": "дон"
      }
    },
    {
      "иванович": {
        "OpencorporaTag": [
          "NOUN",
          "anim",
          "masc",
          "Patr sing",
          "nomn"
        ],
        "normal_form": "иван"
      }
    }
  ],
  [
    {
      "про": {
        "OpencorporaTag": [
          "PREP"
        ],
        "normal_form": "про"
      }
    },
    {
      "тебя": {
        "OpencorporaTag": [
          "NPRO",
          "2per sing",
          "accs"
        ],
        "normal_form": "ты"
      }
    },
    {
      "лежит": {
        "OpencorporaTag": [
          "VERB",
          "impf",
          "intr sing",
          "3per",
          "pres",
          "indc"
        ],
        "normal_form": "лежать"
      }
    },
    {
      "слава": {
        "OpencorporaTag": [
          "NOUN",
          "inan",
          "femn sing",
          "nomn"
        ],
        "normal_form": "слава"
      }
    },
    {
      "добрая": {
        "OpencorporaTag": [
          "ADJF",
          "Qual femn",
          "sing",
          "nomn"
        ],
        "normal_form": "добрый"
      }
    }
  ],
  [
    {
      "слава": {
        "OpencorporaTag": [
          "NOUN",
          "inan",
          "femn sing",
          "nomn"
        ],
        "normal_form": "слава"
      }
    },
    {
      "добрая": {
        "OpencorporaTag": [
          "ADJF",
          "Qual femn",
          "sing",
          "nomn"
        ],
        "normal_form": "добрый"
      }
    },
    {
      "речь": {
        "OpencorporaTag": [
          "NOUN",
          "inan",
          "femn sing",
          "nomn"
        ],
        "normal_form": "речь"
      }
    },
    {
      "хорошая": {
        "OpencorporaTag": [
          "ADJF",
          "Qual femn",
          "sing",
          "nomn"
        ],
        "normal_form": "хороший"
      }
    }
  ],
  [
    {
      "как": {
        "OpencorporaTag": [
          "CONJ"
        ],
        "normal_form": "как"
      }
    },
    {
      "бывало": {
        "OpencorporaTag": [
          "VERB",
          "impf",
          "intr neut",
          "sing",
          "past",
          "indc"
        ],
        "normal_form": "бывать"
      }
    },
    {
      "ты": {
        "OpencorporaTag": [
          "NPRO",
          "2per sing",
          "nomn"
        ],
        "normal_form": "ты"
      }
    },
    {
      "все": {
        "OpencorporaTag": [
          "ADJF",
          "Apro plur",
          "nomn"
        ],
        "normal_form": "весь"
      }
    },
    {
      "быстер": {
        "OpencorporaTag": [
          "NOUN",
          "inan",
          "masc sing",
          "nomn"
        ],
        "normal_form": "быстер"
      }
    },
    {
      "бежишь": {
        "OpencorporaTag": [
          "VERB",
          "perf",
          "intr sing",
          "2per",
          "futr",
          "indc"
        ],
        "normal_form": "бежать"
      }
    }
  ],
  [
    {
      "ты": {
        "OpencorporaTag": [
          "NPRO",
          "2per sing",
          "nomn"
        ],
        "normal_form": "ты"
      }
    },
    {
      "быстер": {
        "OpencorporaTag": [
          "NOUN",
          "inan",
          "masc sing",
          "nomn"
        ],
        "normal_form": "быстер"
      }
    },
    {
      "бежишь": {
        "OpencorporaTag": [
          "VERB",
          "perf",
          "intr sing",
          "2per",
          "futr",
          "indc"
        ],
        "normal_form": "бежать"
      }
    },
    {
      "все": {
        "OpencorporaTag": [
          "ADJF",
          "Apro plur",
          "nomn"
        ],
        "normal_form": "весь"
      }
    },
    {
      "чистехонек": {
        "OpencorporaTag": [
          "ADJS masc",
          "sing"
        ],
        "normal_form": "чистехонький"
      }
    }
  ],
  [
    {
      "а": {
        "OpencorporaTag": [
          "CONJ"
        ],
        "normal_form": "а"
      }
    },
    {
      "теперь": {
        "OpencorporaTag": [
          "ADVB"
        ],
        "normal_form": "теперь"
      }
    },
    {
      "ты": {
        "OpencorporaTag": [
          "NPRO",
          "2per sing",
          "nomn"
        ],
        "normal_form": "ты"
      }
    },
    {
      "кормилец": {
        "OpencorporaTag": [
          "NOUN",
          "anim",
          "masc sing",
          "nomn"
        ],
        "normal_form": "кормилец"
      }
    },
    {
      "все": {
        "OpencorporaTag": [
          "ADJF",
          "Apro plur",
          "nomn"
        ],
        "normal_form": "весь"
      }
    },
    {
      "мутен": {
        "OpencorporaTag": [
          "ADJS",
          "Qual masc",
          "sing"
        ],
        "normal_form": "мутный"
      }
    },
    {
      "течешь": {
        "OpencorporaTag": [
          "VERB",
          "impf",
          "intr sing",
          "2per",
          "pres",
          "indc"
        ],
        "normal_form": "течь"
      }
    }
  ],
  [
    {
      "помутился": {
        "OpencorporaTag": [
          "VERB",
          "perf",
          "intr masc",
          "sing",
          "past",
          "indc"
        ],
        "normal_form": "помутиться"
      }
    },
    {
      "ты": {
        "OpencorporaTag": [
          "NPRO",
          "2per sing",
          "nomn"
        ],
        "normal_form": "ты"
      }
    },
    {
      "дон": {
        "OpencorporaTag": [
          "NOUN",
          "anim",
          "masc",
          "Name sing",
          "nomn"
        ],
        "normal_form": "дон"
      }
    },
    {
      "с": {
        "OpencorporaTag": [
          "PREP"
        ],
        "normal_form": "с"
      }
    },
    {
      "верху": {
        "OpencorporaTag": [
          "NOUN",
          "inan",
          "masc sing",
          "loc2"
        ],
        "normal_form": "верх"
      }
    },
    {
      "до": {
        "OpencorporaTag": [
          "PREP"
        ],
        "normal_form": "до"
      }
    },
    {
      "низу": {
        "OpencorporaTag": [
          "NOUN",
          "inan",
          "masc sing",
          "loc2"
        ],
        "normal_form": "низ"
      }
    }
  ],
  [
    {
      "речь": {
        "OpencorporaTag": [
          "NOUN",
          "inan",
          "femn sing",
          "nomn"
        ],
        "normal_form": "речь"
      }
    },
    {
      "возговорит": {
        "OpencorporaTag": [
          "VERB",
          "impf",
          "tran sing",
          "3per",
          "pres",
          "indc"
        ],
        "normal_form": "возговорить"
      }
    },
    {
      "славный": {
        "OpencorporaTag": [
          "ADJF",
          "Qual masc",
          "sing",
          "nomn"
        ],
        "normal_form": "славный"
      }
    },
    {
      "тихій": {
        "OpencorporaTag": [
          "VERB",
          "impf",
          "tran sing",
          "impr",
          "excl"
        ],
        "normal_form": "тихіть"
      }
    },
    {
      "дон": {
        "OpencorporaTag": [
          "NOUN",
          "anim",
          "masc",
          "Name sing",
          "nomn"
        ],
        "normal_form": "дон"
      }
    }
  ],
  [
    {
      "уж": {
        "OpencorporaTag": [
          "ADVB"
        ],
        "normal_form": "уж"
      }
    },
    {
      "как-то": {
        "OpencorporaTag": [
          "ADVB"
        ],
        "normal_form": "как-то"
      }
    },
    {
      "мне": {
        "OpencorporaTag": [
          "NPRO",
          "1per sing",
          "datv"
        ],
        "normal_form": "я"
      }
    },
    {
      "все": {
        "OpencorporaTag": [
          "ADJF",
          "Apro plur",
          "nomn"
        ],
        "normal_form": "весь"
      }
    },
    {
      "мутну": {
        "OpencorporaTag": [
          "VERB",
          "perf",
          "tran sing",
          "1per",
          "futr",
          "indc"
        ],
        "normal_form": "мутнуть"
      }
    },
    {
      "не": {
        "OpencorporaTag": [
          "PRCL"
        ],
        "normal_form": "не"
      }
    },
    {
      "быть": {
        "OpencorporaTag": [
          "INFN",
          "impf",
          "intr"
        ],
        "normal_form": "быть"
      }
    }
  ],
  [
    {
      "распустил": {
        "OpencorporaTag": [
          "VERB",
          "perf",
          "tran masc",
          "sing",
          "past",
          "indc"
        ],
        "normal_form": "распустить"
      }
    },
    {
      "я": {
        "OpencorporaTag": [
          "NPRO",
          "1per sing",
          "nomn"
        ],
        "normal_form": "я"
      }
    },
    {
      "своих": {
        "OpencorporaTag": [
          "ADJF",
          "Apro",
          "Anph plur",
          "gent"
        ],
        "normal_form": "свой"
      }
    },
    {
      "ясных": {
        "OpencorporaTag": [
          "ADJF",
          "Qual plur",
          "gent"
        ],
        "normal_form": "ясный"
      }
    },
    {
      "соколов": {
        "OpencorporaTag": [
          "NOUN",
          "anim",
          "masc",
          "Sgtm",
          "Surn sing",
          "nomn"
        ],
        "normal_form": "соколов"
      }
    }
  ],
  [
    {
      "ясных": {
        "OpencorporaTag": [
          "ADJF",
          "Qual plur",
          "gent"
        ],
        "normal_form": "ясный"
      }
    },
    {
      "соколов": {
        "OpencorporaTag": [
          "NOUN",
          "anim",
          "masc",
          "Sgtm",
          "Surn sing",
          "nomn"
        ],
        "normal_form": "соколов"
      }
    },
    {
      "": {
        "OpencorporaTag": [
          "UNKN"
        ],
        "normal_form": ""
      }
    },
    {
      "донскихъ": {
        "OpencorporaTag": [
          "NOUN",
          "anim",
          "masc",
          "Fixd sing",
          "nomn"
        ],
        "normal_form": "донскихъ"
      }
    },
    {
      "казаковъ": {
        "OpencorporaTag": [
          "NOUN",
          "anim",
          "masc",
          "Fixd sing",
          "nomn"
        ],
        "normal_form": "казаковъ"
      }
    }
  ],
  [
    {
      "размываются": {
        "OpencorporaTag": [
          "VERB",
          "impf",
          "intr plur",
          "3per",
          "pres",
          "indc"
        ],
        "normal_form": "размываться"
      }
    },
    {
      "без": {
        "OpencorporaTag": [
          "PREP"
        ],
        "normal_form": "без"
      }
    },
    {
      "них": {
        "OpencorporaTag": [
          "NPRO",
          "3per",
          "Anph plur",
          "gent",
          "Af-p"
        ],
        "normal_form": "они"
      }
    },
    {
      "мои": {
        "OpencorporaTag": [
          "ADJF",
          "Apro plur",
          "nomn"
        ],
        "normal_form": "мой"
      }
    },
    {
      "круты": {
        "OpencorporaTag": [
          "ADJS",
          "Qual plur"
        ],
        "normal_form": "крутой"
      }
    },
    {
      "бережки": {
        "OpencorporaTag": [
          "NOUN",
          "inan",
          "masc plur",
          "nomn"
        ],
        "normal_form": "бережок"
      }
    }
  ],
  [
    {
      "высыпаются": {
        "OpencorporaTag": [
          "VERB",
          "impf",
          "intr plur",
          "3per",
          "pres",
          "indc"
        ],
        "normal_form": "высыпаться"
      }
    },
    {
      "без": {
        "OpencorporaTag": [
          "PREP"
        ],
        "normal_form": "без"
      }
    },
    {
      "них": {
        "OpencorporaTag": [
          "NPRO",
          "3per",
          "Anph plur",
          "gent",
          "Af-p"
        ],
        "normal_form": "они"
      }
    },
    {
      "косы": {
        "OpencorporaTag": [
          "NOUN",
          "inan",
          "femn sing",
          "gent"
        ],
        "normal_form": "коса"
      }
    },
    {
      "желтым": {
        "OpencorporaTag": [
          "ADJF",
          "Qual masc",
          "sing",
          "ablt"
        ],
        "normal_form": "жёлтый"
      }
    },
    {
      "песком": {
        "OpencorporaTag": [
          "NOUN",
          "inan",
          "masc sing",
          "ablt"
        ],
        "normal_form": "песок"
      }
    }
  ]
]