[
  [
    {
      "по": {
        "OpencorporaTag": [
          "PREP"
        ],
        "normal_form": "по"
      }
    },
    {
      "лугу-лугу": {
        "OpencorporaTag": [
          "NOUN",
          "inan",
          "femn",
          "Sgtm",
          "Geox sing",
          "accs"
        ],
        "normal_form": "луга-луга"
      }
    },
    {
      "есть": {
        "OpencorporaTag": [
          "INTJ"
        ],
        "normal_form": "есть"
      }
    },
    {
      "желты": {
        "OpencorporaTag": [
          "ADJS",
          "Qual plur",
          "Infr"
        ],
        "normal_form": "жёлтый"
      }
    },
    {
      "пески": {
        "OpencorporaTag": [
          "NOUN",
          "inan",
          "masc plur",
          "nomn"
        ],
        "normal_form": "песок"
      }
    }
  ],
  [
    {
      "тут": {
        "OpencorporaTag": [
          "ADVB",
          "Dmns"
        ],
        "normal_form": "тут"
      }
    },
    {
      "и": {
        "OpencorporaTag": [
          "CONJ"
        ],
        "normal_form": "и"
      }
    },
    {
      "шли-прошли": {
        "OpencorporaTag": [
          "VERB",
          "impf",
          "intr plur",
          "past",
          "indc"
        ],
        "normal_form": "идти-пройти"
      }
    },
    {
      "две": {
        "OpencorporaTag": [
          "NUMR femn",
          "nomn"
        ],
        "normal_form": "два"
      }
    },
    {
      "родныя": {
        "OpencorporaTag": [
          "NOUN",
          "anim",
          "masc",
          "Name sing",
          "gent"
        ],
        "normal_form": "родный"
      }
    },
    {
      "сестры": {
        "OpencorporaTag": [
          "NOUN",
          "anim",
          "femn sing",
          "gent"
        ],
        "normal_form": "сестра"
      }
    }
  ],
  [
    {
      "что": {
        "OpencorporaTag": [
          "CONJ"
        ],
        "normal_form": "что"
      }
    },
    {
      "большая-то": {
        "OpencorporaTag": [
          "ADJF",
          "Qual femn",
          "sing",
          "nomn"
        ],
        "normal_form": "большой-то"
      }
    },
    {
      "меньшую": {
        "OpencorporaTag": [
          "ADJF femn",
          "sing",
          "accs"
        ],
        "normal_form": "меньший"
      }
    },
    {
      "уговаривала": {
        "OpencorporaTag": [
          "VERB",
          "impf",
          "tran femn",
          "sing",
          "past",
          "indc"
        ],
        "normal_form": "уговаривать"
      }
    }
  ],
  [
    {
      "не": {
        "OpencorporaTag": [
          "PRCL"
        ],
        "normal_form": "не"
      }
    },
    {
      "сиди-ка": {
        "OpencorporaTag": [
          "VERB",
          "impf",
          "intr sing",
          "impr",
          "excl"
        ],
        "normal_form": "сидеть-ка"
      }
    },
    {
      "ты": {
        "OpencorporaTag": [
          "NPRO",
          "2per sing",
          "nomn"
        ],
        "normal_form": "ты"
      }
    },
    {
      "сестрица": {
        "OpencorporaTag": [
          "NOUN",
          "anim",
          "femn sing",
          "nomn"
        ],
        "normal_form": "сестрица"
      }
    },
    {
      "одна": {
        "OpencorporaTag": [
          "ADJF",
          "Apro femn",
          "sing",
          "nomn"
        ],
        "normal_form": "один"
      }
    },
    {
      "в": {
        "OpencorporaTag": [
          "PREP"
        ],
        "normal_form": "в"
      }
    },
    {
      "терему": {
        "OpencorporaTag": [
          "NOUN",
          "inan",
          "masc sing",
          "datv"
        ],
        "normal_form": "терем"
      }
    }
  ],
  [
    {
      "не": {
        "OpencorporaTag": [
          "PRCL"
        ],
        "normal_form": "не"
      }
    },
    {
      "отворяй-ка": {
        "OpencorporaTag": [
          "VERB",
          "impf",
          "tran sing",
          "impr",
          "excl"
        ],
        "normal_form": "отворять-ка"
      }
    },
    {
      "родимая": {
        "OpencorporaTag": [
          "ADJF",
          "Qual femn",
          "sing",
          "nomn"
        ],
        "normal_form": "родимый"
      }
    },
    {
      "окошечко": {
        "OpencorporaTag": [
          "NOUN",
          "inan",
          "neut sing",
          "nomn"
        ],
        "normal_form": "окошечко"
      }
    }
  ],
  [
    {
      "неравно": {
        "OpencorporaTag": [
          "PRCL"
        ],
        "normal_form": "неравно"
      }
    },
    {
      "к": {
        "OpencorporaTag": [
          "PREP"
        ],
        "normal_form": "к"
      }
    },
    {
      "тебе": {
        "OpencorporaTag": [
          "NPRO",
          "2per sing",
          "datv"
        ],
        "normal_form": "ты"
      }
    },
    {
      "сестрица": {
        "OpencorporaTag": [
          "NOUN",
          "anim",
          "femn sing",
          "nomn"
        ],
        "normal_form": "сестрица"
      }
    },
    {
      "соколик": {
        "OpencorporaTag": [
          "NOUN",
          "anim",
          "masc sing",
          "nomn"
        ],
        "normal_form": "соколик"
      }
    },
    {
      "залетить": {
        "OpencorporaTag": [
          "INFN",
          "perf",
          "tran"
        ],
        "normal_form": "залетить"
      }
    }
  ],
  [
    {
      "соколик": {
        "OpencorporaTag": [
          "NOUN",
          "anim",
          "masc sing",
          "nomn"
        ],
        "normal_form": "соколик"
      }
    },
    {
      "залетит": {
        "OpencorporaTag": [
          "VERB",
          "perf",
          "intr sing",
          "3per",
          "futr",
          "indc"
        ],
        "normal_form": "залететь"
      }
    },
    {
      "молодец": {
        "OpencorporaTag": [
          "NOUN",
          "anim",
          "masc sing",
          "nomn"
        ],
        "normal_form": "молодец"
      }
    },
    {
      "зайдет": {
        "OpencorporaTag": [
          "VERB",
          "perf",
          "intr sing",
          "3per",
          "futr",
          "indc"
        ],
        "normal_form": "зайти"
      }
    }
  ],
  [
    {
      "поцелует": {
        "OpencorporaTag": [
          "VERB",
          "perf",
          "tran sing",
          "3per",
          "futr",
          "indc"
        ],
        "normal_form": "поцеловать"
      }
    },
    {
      "да": {
        "OpencorporaTag": [
          "PRCL"
        ],
        "normal_form": "да"
      }
    },
    {
      "уйдет": {
        "OpencorporaTag": [
          "VERB",
          "perf",
          "intr sing",
          "3per",
          "futr",
          "indc"
        ],
        "normal_form": "уйти"
      }
    }
  ]
]