[
  [
    {
      "сад": {
        "OpencorporaTag": [
          "NOUN",
          "inan",
          "masc sing",
          "nomn"
        ],
        "normal_form": "сад"
      }
    },
    {
      "ли": {
        "OpencorporaTag": [
          "PRCL"
        ],
        "normal_form": "ли"
      }
    },
    {
      "мой": {
        "OpencorporaTag": [
          "ADJF",
          "Apro masc",
          "sing",
          "nomn"
        ],
        "normal_form": "мой"
      }
    },
    {
      "сад": {
        "OpencorporaTag": [
          "NOUN",
          "inan",
          "masc sing",
          "nomn"
        ],
        "normal_form": "сад"
      }
    },
    {
      "зеленый": {
        "OpencorporaTag": [
          "ADJF",
          "Qual masc",
          "sing",
          "nomn"
        ],
        "normal_form": "зелёный"
      }
    },
    {
      "виноград": {
        "OpencorporaTag": [
          "NOUN",
          "inan",
          "masc sing",
          "nomn"
        ],
        "normal_form": "виноград"
      }
    }
  ],
  [
    {
      "хорошо-то": {
        "OpencorporaTag": [
          "ADVB",
          "Prdx"
        ],
        "normal_form": "хорошо-то"
      }
    },
    {
      "во": {
        "OpencorporaTag": [
          "PREP Vpre"
        ],
        "normal_form": "в"
      }
    },
    {
      "саду": {
        "OpencorporaTag": [
          "NOUN",
          "inan",
          "masc sing",
          "loc2"
        ],
        "normal_form": "сад"
      }
    },
    {
      "мелки": {
        "OpencorporaTag": [
          "NOUN",
          "inan",
          "masc plur",
          "nomn"
        ],
        "normal_form": "мелок"
      }
    },
    {
      "пташечки": {
        "OpencorporaTag": [
          "NOUN",
          "anim",
          "femn sing",
          "gent"
        ],
        "normal_form": "пташечка"
      }
    },
    {
      "поют": {
        "OpencorporaTag": [
          "VERB",
          "impf",
          "tran plur",
          "3per",
          "pres",
          "indc"
        ],
        "normal_form": "петь"
      }
    }
  ],
  [
    {
      "а": {
        "OpencorporaTag": [
          "CONJ"
        ],
        "normal_form": "а"
      }
    },
    {
      "меня": {
        "OpencorporaTag": [
          "NPRO",
          "1per sing",
          "accs"
        ],
        "normal_form": "я"
      }
    },
    {
      "ли": {
        "OpencorporaTag": [
          "PRCL"
        ],
        "normal_form": "ли"
      }
    },
    {
      "молоденьку": {
        "OpencorporaTag": [
          "NOUN",
          "inan",
          "masc sing",
          "datv"
        ],
        "normal_form": "молоденёк"
      }
    },
    {
      "грусть-тоска-печаль": {
        "OpencorporaTag": [
          "VERB",
          "perf",
          "tran sing",
          "impr",
          "excl"
        ],
        "normal_form": "грусть-тоска-печалить"
      }
    },
    {
      "берет": {
        "OpencorporaTag": [
          "VERB",
          "impf",
          "tran sing",
          "3per",
          "pres",
          "indc"
        ],
        "normal_form": "брать"
      }
    }
  ],
  [
    {
      "за": {
        "OpencorporaTag": [
          "PREP"
        ],
        "normal_form": "за"
      }
    },
    {
      "что": {
        "OpencorporaTag": [
          "CONJ"
        ],
        "normal_form": "что"
      }
    },
    {
      "жизнь": {
        "OpencorporaTag": [
          "NOUN",
          "inan",
          "femn sing",
          "accs"
        ],
        "normal_form": "жизнь"
      }
    },
    {
      "моя": {
        "OpencorporaTag": [
          "ADJF",
          "Apro femn",
          "sing",
          "nomn"
        ],
        "normal_form": "мой"
      }
    },
    {
      "не": {
        "OpencorporaTag": [
          "PRCL"
        ],
        "normal_form": "не"
      }
    },
    {
      "знаешься": {
        "OpencorporaTag": [
          "VERB",
          "impf",
          "intr sing",
          "2per",
          "pres",
          "indc"
        ],
        "normal_form": "знаться"
      }
    },
    {
      "со": {
        "OpencorporaTag": [
          "PREP Vpre"
        ],
        "normal_form": "с"
      }
    },
    {
      "мной": {
        "OpencorporaTag": [
          "NPRO",
          "1per sing",
          "ablt"
        ],
        "normal_form": "я"
      }
    }
  ],
  [
    {
      "иль": {
        "OpencorporaTag": [
          "CONJ"
        ],
        "normal_form": "иль"
      }
    },
    {
      "за": {
        "OpencorporaTag": [
          "PREP"
        ],
        "normal_form": "за"
      }
    },
    {
      "скудость": {
        "OpencorporaTag": [
          "NOUN",
          "inan",
          "femn sing",
          "nomn"
        ],
        "normal_form": "скудость"
      }
    },
    {
      "иль": {
        "OpencorporaTag": [
          "CONJ"
        ],
        "normal_form": "иль"
      }
    },
    {
      "за": {
        "OpencorporaTag": [
          "PREP"
        ],
        "normal_form": "за"
      }
    },
    {
      "бедность": {
        "OpencorporaTag": [
          "NOUN",
          "inan",
          "femn sing",
          "nomn"
        ],
        "normal_form": "бедность"
      }
    },
    {
      "за": {
        "OpencorporaTag": [
          "PREP"
        ],
        "normal_form": "за"
      }
    },
    {
      "мою": {
        "OpencorporaTag": [
          "ADJF",
          "Apro femn",
          "sing",
          "accs"
        ],
        "normal_form": "мой"
      }
    }
  ],
  [
    {
      "иль": {
        "OpencorporaTag": [
          "CONJ"
        ],
        "normal_form": "иль"
      }
    },
    {
      "не": {
        "OpencorporaTag": [
          "PRCL"
        ],
        "normal_form": "не"
      }
    },
    {
      "кажется": {
        "OpencorporaTag": [
          "CONJ",
          "Prnt"
        ],
        "normal_form": "кажется"
      }
    },
    {
      "красота": {
        "OpencorporaTag": [
          "NOUN",
          "inan",
          "femn sing",
          "nomn"
        ],
        "normal_form": "красота"
      }
    },
    {
      "тебе": {
        "OpencorporaTag": [
          "NPRO",
          "2per sing",
          "datv"
        ],
        "normal_form": "ты"
      }
    },
    {
      "моя": {
        "OpencorporaTag": [
          "ADJF",
          "Apro femn",
          "sing",
          "nomn"
        ],
        "normal_form": "мой"
      }
    }
  ],
  [
    {
      "я": {
        "OpencorporaTag": [
          "NPRO",
          "1per sing",
          "nomn"
        ],
        "normal_form": "я"
      }
    },
    {
      "могу": {
        "OpencorporaTag": [
          "VERB",
          "impf",
          "intr sing",
          "1per",
          "pres",
          "indc"
        ],
        "normal_form": "мочь"
      }
    },
    {
      "дружок": {
        "OpencorporaTag": [
          "NOUN",
          "anim",
          "masc sing",
          "nomn"
        ],
        "normal_form": "дружок"
      }
    },
    {
      "прибавить": {
        "OpencorporaTag": [
          "INFN",
          "perf",
          "tran"
        ],
        "normal_form": "прибавить"
      }
    },
    {
      "красоты": {
        "OpencorporaTag": [
          "NOUN",
          "inan",
          "femn sing",
          "gent"
        ],
        "normal_form": "красота"
      }
    }
  ],
  [
    {
      "набелюсь": {
        "OpencorporaTag": [
          "VERB",
          "perf",
          "intr sing",
          "1per",
          "futr",
          "indc"
        ],
        "normal_form": "набелиться"
      }
    },
    {
      "я": {
        "OpencorporaTag": [
          "NPRO",
          "1per sing",
          "nomn"
        ],
        "normal_form": "я"
      }
    },
    {
      "нарумянюсь": {
        "OpencorporaTag": [
          "VERB",
          "perf",
          "intr sing",
          "1per",
          "futr",
          "indc"
        ],
        "normal_form": "нарумяниться"
      }
    },
    {
      "молода": {
        "OpencorporaTag": [
          "ADJS",
          "Qual femn",
          "sing"
        ],
        "normal_form": "молодой"
      }
    }
  ],
  [
    {
      "я": {
        "OpencorporaTag": [
          "NPRO",
          "1per sing",
          "nomn"
        ],
        "normal_form": "я"
      }
    },
    {
      "надену": {
        "OpencorporaTag": [
          "VERB",
          "perf",
          "tran sing",
          "1per",
          "futr",
          "indc"
        ],
        "normal_form": "надеть"
      }
    },
    {
      "цветно": {
        "OpencorporaTag": [
          "ADJS neut",
          "sing"
        ],
        "normal_form": "цветный"
      }
    },
    {
      "платье": {
        "OpencorporaTag": [
          "NOUN",
          "inan",
          "neut sing",
          "nomn"
        ],
        "normal_form": "платье"
      }
    },
    {
      "на": {
        "OpencorporaTag": [
          "PREP"
        ],
        "normal_form": "на"
      }
    },
    {
      "себя": {
        "OpencorporaTag": [
          "NPRO",
          "Anph sing",
          "accs"
        ],
        "normal_form": "себя"
      }
    }
  ],
  [
    {
      "мы": {
        "OpencorporaTag": [
          "NPRO",
          "1per plur",
          "nomn"
        ],
        "normal_form": "мы"
      }
    },
    {
      "поедем": {
        "OpencorporaTag": [
          "VERB",
          "perf",
          "intr plur",
          "1per",
          "futr",
          "indc"
        ],
        "normal_form": "поехать"
      }
    },
    {
      "во": {
        "OpencorporaTag": [
          "PREP Vpre"
        ],
        "normal_form": "в"
      }
    },
    {
      "зеленый": {
        "OpencorporaTag": [
          "ADJF",
          "Qual masc",
          "sing",
          "nomn"
        ],
        "normal_form": "зелёный"
      }
    },
    {
      "сад": {
        "OpencorporaTag": [
          "NOUN",
          "inan",
          "masc sing",
          "nomn"
        ],
        "normal_form": "сад"
      }
    },
    {
      "гулять": {
        "OpencorporaTag": [
          "INFN",
          "impf",
          "intr"
        ],
        "normal_form": "гулять"
      }
    }
  ],
  [
    {
      "сорвем": {
        "OpencorporaTag": [
          "VERB",
          "perf",
          "tran plur",
          "1per",
          "futr",
          "indc"
        ],
        "normal_form": "сорвать"
      }
    },
    {
      "с": {
        "OpencorporaTag": [
          "PREP"
        ],
        "normal_form": "с"
      }
    },
    {
      "травушки": {
        "OpencorporaTag": [
          "NOUN",
          "inan",
          "femn sing",
          "gent"
        ],
        "normal_form": "травушка"
      }
    },
    {
      "там": {
        "OpencorporaTag": [
          "ADVB",
          "Dmns"
        ],
        "normal_form": "там"
      }
    },
    {
      "аленькй": {
        "OpencorporaTag": [
          "VERB",
          "impf",
          "tran sing",
          "impr",
          "excl"
        ],
        "normal_form": "аленькть"
      }
    },
    {
      "цветок": {
        "OpencorporaTag": [
          "NOUN",
          "inan",
          "masc sing",
          "nomn"
        ],
        "normal_form": "цветок"
      }
    }
  ],
  [
    {
      "совьем-совьем": {
        "OpencorporaTag": [
          "ADJF",
          "Poss masc",
          "sing",
          "loct"
        ],
        "normal_form": "совий-совий"
      }
    },
    {
      "на": {
        "OpencorporaTag": [
          "PREP"
        ],
        "normal_form": "на"
      }
    },
    {
      "головушку": {
        "OpencorporaTag": [
          "NOUN",
          "inan",
          "femn sing",
          "accs"
        ],
        "normal_form": "головушка"
      }
    },
    {
      "венок": {
        "OpencorporaTag": [
          "NOUN",
          "anim",
          "femn plur",
          "gent"
        ],
        "normal_form": "венка"
      }
    }
  ]
]